{
    "37620833-52ab-ea56-31cb-83443e3e22dd": {
        "paletteKey": "FlexLayoutCol",
        "designerReference": [
            {
                "_key": "componentLabel",
                "_value": "Column",
                "_type": "kv",
                "_attrDef": "p",
                "_useAsLabel": true
            },
            {
                "_key": "style",
                "_value": "",
                "_type": "kv",
                "_attrDef": "p"
            },
            {
                "_key": "class",
                "_value": [
                    "refferal_message_class"
                ],
                "_type": "dav",
                "_attrDef": "p"
            },
            {
                "_key": "fxFlex",
                "_value": "",
                "_type": "kv",
                "_attrDef": "p"
            },
            {
                "_key": "fxLayoutGap",
                "_value": "",
                "_type": "kv",
                "_attrDef": "p"
            },
            {
                "_key": "wrap",
                "_value": "wrap",
                "_type": "a",
                "_attrDef": "p"
            },
            {
                "_key": "layoutAlign",
                "_value": "start",
                "_type": "a",
                "_attrDef": "p"
            },
            {
                "_key": "pLayoutAlign",
                "_value": "stretch",
                "_type": "a",
                "_attrDef": "p"
            },
            {
                "_key": "[fxShow]",
                "_value": "true",
                "_type": "kv",
                "_attrDef": "p"
            },
            {
                "_key": "[fxHide]",
                "_value": "false",
                "_type": "kv",
                "_attrDef": "p"
            }
        ],
        "75091e68-012e-a5b4-aa31-97c9e54eaef9": {
            "paletteKey": "FlexLayoutRow",
            "parentEditorKey": "37620833-52ab-ea56-31cb-83443e3e22dd",
            "designerReference": [
                {
                    "_key": "componentLabel",
                    "_value": "Row",
                    "_type": "kv",
                    "_attrDef": "p",
                    "_useAsLabel": true
                },
                {
                    "_key": "style",
                    "_value": "",
                    "_type": "kv",
                    "_attrDef": "p"
                },
                {
                    "_key": "class",
                    "_value": "",
                    "_type": "dav",
                    "_attrDef": "p"
                },
                {
                    "_key": "fxFlex",
                    "_value": "",
                    "_type": "kv",
                    "_attrDef": "p"
                },
                {
                    "_key": "fxLayoutGap",
                    "_value": "",
                    "_type": "kv",
                    "_attrDef": "p"
                },
                {
                    "_key": "wrap",
                    "_value": "wrap",
                    "_type": "a",
                    "_attrDef": "p"
                },
                {
                    "_key": "layoutAlign",
                    "_value": "space-evenly",
                    "_type": "a",
                    "_attrDef": "p"
                },
                {
                    "_key": "pLayoutAlign",
                    "_value": "center",
                    "_type": "a",
                    "_attrDef": "p"
                },
                {
                    "_key": "[fxShow]",
                    "_value": "true",
                    "_type": "kv",
                    "_attrDef": "p"
                },
                {
                    "_key": "[fxHide]",
                    "_value": "false",
                    "_type": "kv",
                    "_attrDef": "p"
                }
            ],
            "df9e19c4-8862-e9d5-f7da-9adfde4ade6b": {
                "paletteKey": "FlexLayoutRow",
                "parentEditorKey": "75091e68-012e-a5b4-aa31-97c9e54eaef9",
                "designerReference": [
                    {
                        "_key": "componentLabel",
                        "_value": "Row",
                        "_type": "kv",
                        "_attrDef": "p",
                        "_useAsLabel": true
                    },
                    {
                        "_key": "style",
                        "_value": "",
                        "_type": "kv",
                        "_attrDef": "p"
                    },
                    {
                        "_key": "class",
                        "_value": "",
                        "_type": "dav",
                        "_attrDef": "p"
                    },
                    {
                        "_key": "fxFlex",
                        "_value": "50",
                        "_type": "kv",
                        "_attrDef": "p"
                    },
                    {
                        "_key": "fxLayoutGap",
                        "_value": "",
                        "_type": "kv",
                        "_attrDef": "p"
                    },
                    {
                        "_key": "wrap",
                        "_value": "wrap",
                        "_type": "a",
                        "_attrDef": "p"
                    },
                    {
                        "_key": "layoutAlign",
                        "_value": "start",
                        "_type": "a",
                        "_attrDef": "p"
                    },
                    {
                        "_key": "pLayoutAlign",
                        "_value": "start",
                        "_type": "a",
                        "_attrDef": "p"
                    },
                    {
                        "_key": "[fxShow]",
                        "_value": "true",
                        "_type": "kv",
                        "_attrDef": "p"
                    },
                    {
                        "_key": "[fxHide]",
                        "_value": "false",
                        "_type": "kv",
                        "_attrDef": "p"
                    }
                ],
                "e6b801f5-8bcb-b333-c1f7-51d3c4de96b7": {
                    "paletteKey": "NG-image",
                    "parentEditorKey": "df9e19c4-8862-e9d5-f7da-9adfde4ade6b",
                    "designerReference": [
                        {
                            "_key": "componentLabel",
                            "_value": "ingredion",
                            "_type": "kv",
                            "_attrDef": "p",
                            "_useAsLabel": true
                        },
                        {
                            "_key": "style",
                            "_value": "padding:0.25em 0.25em;",
                            "_type": "kv",
                            "_attrDef": "p"
                        },
                        {
                            "_key": "class",
                            "_value": "",
                            "_type": "dav",
                            "_attrDef": "p"
                        },
                        {
                            "_key": "imgSrc",
                            "_value": "Android/logo.png",
                            "_type": "kv",
                            "_attrDef": "p"
                        },
                        {
                            "_key": "alt",
                            "_value": "",
                            "_type": "kv",
                            "_attrDef": "p"
                        },
                        {
                            "_key": "[src]",
                            "_value": "",
                            "_type": "kv",
                            "_attrDef": "p"
                        },
                        {
                            "_key": "imgSecure",
                            "_value": "",
                            "_type": "a",
                            "_attrDef": "p"
                        },
                        {
                            "_key": "[collectionName]",
                            "_value": "",
                            "_type": "kv",
                            "_attrDef": "p"
                        },
                        {
                            "_key": "[imageFilter]",
                            "_value": "",
                            "_type": "kv",
                            "_attrDef": "p"
                        },
                        {
                            "_key": "width",
                            "_value": "",
                            "_type": "kv",
                            "_attrDef": "p"
                        },
                        {
                            "_key": "srcset",
                            "_value": "",
                            "_type": "kv",
                            "_attrDef": "p"
                        },
                        {
                            "_key": "sizes",
                            "_value": "",
                            "_type": "kv",
                            "_attrDef": "p"
                        }
                    ]
                }
            },
            "3230d138-48f8-2b2f-f4ce-7f500f261e84": {
                "paletteKey": "FlexLayoutRow",
                "parentEditorKey": "75091e68-012e-a5b4-aa31-97c9e54eaef9",
                "designerReference": [
                    {
                        "_key": "componentLabel",
                        "_value": "Row",
                        "_type": "kv",
                        "_attrDef": "p",
                        "_useAsLabel": true
                    },
                    {
                        "_key": "style",
                        "_value": "",
                        "_type": "kv",
                        "_attrDef": "p"
                    },
                    {
                        "_key": "class",
                        "_value": "",
                        "_type": "dav",
                        "_attrDef": "p"
                    },
                    {
                        "_key": "fxFlex",
                        "_value": "50",
                        "_type": "kv",
                        "_attrDef": "p"
                    },
                    {
                        "_key": "fxLayoutGap",
                        "_value": "",
                        "_type": "kv",
                        "_attrDef": "p"
                    },
                    {
                        "_key": "wrap",
                        "_value": "wrap",
                        "_type": "a",
                        "_attrDef": "p"
                    },
                    {
                        "_key": "layoutAlign",
                        "_value": "end",
                        "_type": "a",
                        "_attrDef": "p"
                    },
                    {
                        "_key": "pLayoutAlign",
                        "_value": "end",
                        "_type": "a",
                        "_attrDef": "p"
                    },
                    {
                        "_key": "[fxShow]",
                        "_value": "true",
                        "_type": "kv",
                        "_attrDef": "p"
                    },
                    {
                        "_key": "[fxHide]",
                        "_value": "false",
                        "_type": "kv",
                        "_attrDef": "p"
                    }
                ],
                "ae1ee14c-abab-ae9b-bc70-bc71229585da": {
                    "paletteKey": "NG-image",
                    "parentEditorKey": "3230d138-48f8-2b2f-f4ce-7f500f261e84",
                    "designerReference": [
                        {
                            "_key": "componentLabel",
                            "_value": "logout",
                            "_type": "kv",
                            "_attrDef": "p",
                            "_useAsLabel": true
                        },
                        {
                            "_key": "style",
                            "_value": "padding:0.45em 0.45em;",
                            "_type": "kv",
                            "_attrDef": "p"
                        },
                        {
                            "_key": "class",
                            "_value": "",
                            "_type": "dav",
                            "_attrDef": "p"
                        },
                        {
                            "_key": "imgSrc",
                            "_value": "Android/logout.png",
                            "_type": "kv",
                            "_attrDef": "p"
                        },
                        {
                            "_key": "alt",
                            "_value": "",
                            "_type": "kv",
                            "_attrDef": "p"
                        },
                        {
                            "_key": "[src]",
                            "_value": "",
                            "_type": "kv",
                            "_attrDef": "p"
                        },
                        {
                            "_key": "imgSecure",
                            "_value": "",
                            "_type": "a",
                            "_attrDef": "p"
                        },
                        {
                            "_key": "[collectionName]",
                            "_value": "",
                            "_type": "kv",
                            "_attrDef": "p"
                        },
                        {
                            "_key": "[imageFilter]",
                            "_value": "",
                            "_type": "kv",
                            "_attrDef": "p"
                        },
                        {
                            "_key": "width",
                            "_value": "",
                            "_type": "kv",
                            "_attrDef": "p"
                        },
                        {
                            "_key": "srcset",
                            "_value": "",
                            "_type": "kv",
                            "_attrDef": "p"
                        },
                        {
                            "_key": "sizes",
                            "_value": "",
                            "_type": "kv",
                            "_attrDef": "p"
                        }
                    ]
                }
            }
        },
        "9fd1622a-7461-4520-a543-1b19da053f62": {
            "paletteKey": "FlexLayoutCol",
            "parentEditorKey": "37620833-52ab-ea56-31cb-83443e3e22dd",
            "designerReference": [
                {
                    "_key": "componentLabel",
                    "_value": "Column",
                    "_type": "kv",
                    "_attrDef": "p",
                    "_useAsLabel": true
                },
                {
                    "_key": "style",
                    "_value": "font-family: Poppins; font-style: normal; font-weight: 300; font-size: 1em; line-height: 2em; display: flex; align-items: center; text-align: center; letter-spacing: 0.05em; text-transform: capitalize;",
                    "_type": "kv",
                    "_attrDef": "p"
                },
                {
                    "_key": "class",
                    "_value": "",
                    "_type": "dav",
                    "_attrDef": "p"
                },
                {
                    "_key": "fxFlex",
                    "_value": "",
                    "_type": "kv",
                    "_attrDef": "p"
                },
                {
                    "_key": "fxLayoutGap",
                    "_value": "",
                    "_type": "kv",
                    "_attrDef": "p"
                },
                {
                    "_key": "wrap",
                    "_value": "wrap",
                    "_type": "a",
                    "_attrDef": "p"
                },
                {
                    "_key": "layoutAlign",
                    "_value": "start",
                    "_type": "a",
                    "_attrDef": "p"
                },
                {
                    "_key": "pLayoutAlign",
                    "_value": "center",
                    "_type": "a",
                    "_attrDef": "p"
                },
                {
                    "_key": "[fxShow]",
                    "_value": "true",
                    "_type": "kv",
                    "_attrDef": "p"
                },
                {
                    "_key": "[fxHide]",
                    "_value": "false",
                    "_type": "kv",
                    "_attrDef": "p"
                }
            ],
            "c8f3d0d0-5c32-8211-afca-bb01ce046480": {
                "paletteKey": "NG-image",
                "parentEditorKey": "9fd1622a-7461-4520-a543-1b19da053f62",
                "designerReference": [
                    {
                        "_key": "componentLabel",
                        "_value": "successLogo",
                        "_type": "kv",
                        "_attrDef": "p",
                        "_useAsLabel": true
                    },
                    {
                        "_key": "style",
                        "_value": "",
                        "_type": "kv",
                        "_attrDef": "p"
                    },
                    {
                        "_key": "class",
                        "_value": [
                            "success_logo"
                        ],
                        "_type": "dav",
                        "_attrDef": "p"
                    },
                    {
                        "_key": "imgSrc",
                        "_value": "Android/Group29.png",
                        "_type": "kv",
                        "_attrDef": "p"
                    },
                    {
                        "_key": "alt",
                        "_value": "",
                        "_type": "kv",
                        "_attrDef": "p"
                    },
                    {
                        "_key": "[src]",
                        "_value": "",
                        "_type": "kv",
                        "_attrDef": "p"
                    },
                    {
                        "_key": "imgSecure",
                        "_value": "",
                        "_type": "a",
                        "_attrDef": "p"
                    },
                    {
                        "_key": "[collectionName]",
                        "_value": "",
                        "_type": "kv",
                        "_attrDef": "p"
                    },
                    {
                        "_key": "[imageFilter]",
                        "_value": "",
                        "_type": "kv",
                        "_attrDef": "p"
                    },
                    {
                        "_key": "width",
                        "_value": "",
                        "_type": "kv",
                        "_attrDef": "p"
                    },
                    {
                        "_key": "srcset",
                        "_value": "",
                        "_type": "kv",
                        "_attrDef": "p"
                    },
                    {
                        "_key": "sizes",
                        "_value": "",
                        "_type": "kv",
                        "_attrDef": "p"
                    }
                ]
            },
            "c09b7c46-a8d6-f2da-bfff-9ea012cd5403": {
                "paletteKey": "FlexLayoutCol",
                "parentEditorKey": "9fd1622a-7461-4520-a543-1b19da053f62",
                "designerReference": [
                    {
                        "_key": "componentLabel",
                        "_value": "Column",
                        "_type": "kv",
                        "_attrDef": "p",
                        "_useAsLabel": true
                    },
                    {
                        "_key": "style",
                        "_value": "",
                        "_type": "kv",
                        "_attrDef": "p"
                    },
                    {
                        "_key": "class",
                        "_value": "",
                        "_type": "dav",
                        "_attrDef": "p"
                    },
                    {
                        "_key": "fxFlex",
                        "_value": "",
                        "_type": "kv",
                        "_attrDef": "p"
                    },
                    {
                        "_key": "fxLayoutGap",
                        "_value": "",
                        "_type": "kv",
                        "_attrDef": "p"
                    },
                    {
                        "_key": "wrap",
                        "_value": "wrap",
                        "_type": "a",
                        "_attrDef": "p"
                    },
                    {
                        "_key": "layoutAlign",
                        "_value": "space-around",
                        "_type": "a",
                        "_attrDef": "p"
                    },
                    {
                        "_key": "pLayoutAlign",
                        "_value": "center",
                        "_type": "a",
                        "_attrDef": "p"
                    },
                    {
                        "_key": "[fxShow]",
                        "_value": "true",
                        "_type": "kv",
                        "_attrDef": "p"
                    },
                    {
                        "_key": "[fxHide]",
                        "_value": "false",
                        "_type": "kv",
                        "_attrDef": "p"
                    }
                ],
                "0050f7ff-4a47-ce09-d4f6-7d6f53c83f26": {
                    "paletteKey": "FlexLayoutRow",
                    "parentEditorKey": "c09b7c46-a8d6-f2da-bfff-9ea012cd5403",
                    "designerReference": [
                        {
                            "_key": "componentLabel",
                            "_value": "Row",
                            "_type": "kv",
                            "_attrDef": "p",
                            "_useAsLabel": true
                        },
                        {
                            "_key": "style",
                            "_value": "",
                            "_type": "kv",
                            "_attrDef": "p"
                        },
                        {
                            "_key": "class",
                            "_value": "",
                            "_type": "dav",
                            "_attrDef": "p"
                        },
                        {
                            "_key": "fxFlex",
                            "_value": "",
                            "_type": "kv",
                            "_attrDef": "p"
                        },
                        {
                            "_key": "fxLayoutGap",
                            "_value": "",
                            "_type": "kv",
                            "_attrDef": "p"
                        },
                        {
                            "_key": "wrap",
                            "_value": "wrap",
                            "_type": "a",
                            "_attrDef": "p"
                        },
                        {
                            "_key": "layoutAlign",
                            "_value": "center",
                            "_type": "a",
                            "_attrDef": "p"
                        },
                        {
                            "_key": "pLayoutAlign",
                            "_value": "center",
                            "_type": "a",
                            "_attrDef": "p"
                        },
                        {
                            "_key": "[fxShow]",
                            "_value": "true",
                            "_type": "kv",
                            "_attrDef": "p"
                        },
                        {
                            "_key": "[fxHide]",
                            "_value": "false",
                            "_type": "kv",
                            "_attrDef": "p"
                        }
                    ],
                    "9ce2b954-e2db-d48f-a0d7-a95f15996520": {
                        "paletteKey": "Html5",
                        "parentEditorKey": "0050f7ff-4a47-ce09-d4f6-7d6f53c83f26",
                        "isAdvancedComponent": true,
                        "designerReference": [
                            {
                                "_key": "style",
                                "_value": "",
                                "_type": "kv",
                                "_attrDef": "p"
                            },
                            {
                                "_key": "class",
                                "_value": [
                                    "thankyou"
                                ],
                                "_type": "dav",
                                "_attrDef": "p"
                            },
                            {
                                "_key": "htmlElement",
                                "_value": "div",
                                "_type": "dav",
                                "_attrDef": "p",
                                "_useAsLabel": true
                            },
                            {
                                "_key": "tagType",
                                "_value": "div",
                                "_type": "a",
                                "_attrDef": "p",
                                "_visibility": false
                            },
                            {
                                "_key": "name",
                                "_value": "",
                                "_type": "kv",
                                "_attrDef": "p",
                                "_visibility": false
                            },
                            {
                                "_key": "sandbox",
                                "_value": "",
                                "_type": "kv",
                                "_attrDef": "p",
                                "_visibility": false
                            },
                            {
                                "_key": "src",
                                "_value": "",
                                "_type": "kv",
                                "_attrDef": "p",
                                "_visibility": false
                            },
                            {
                                "_key": "srcdoc",
                                "_value": "",
                                "_type": "kv",
                                "_attrDef": "p",
                                "_visibility": false
                            },
                            {
                                "_key": "width",
                                "_value": "",
                                "_type": "kv",
                                "_attrDef": "p",
                                "_visibility": false
                            },
                            {
                                "_key": "[autoplay]",
                                "_value": "",
                                "_type": "kv",
                                "_attrDef": "p",
                                "_visibility": false
                            },
                            {
                                "_key": "[loop]",
                                "_value": "",
                                "_type": "kv",
                                "_attrDef": "p",
                                "_visibility": false
                            },
                            {
                                "_key": "data",
                                "_value": "",
                                "_type": "kv",
                                "_attrDef": "p",
                                "_visibility": false
                            },
                            {
                                "_key": "audioSource",
                                "_value": [],
                                "_type": "a",
                                "_attrDef": "p",
                                "_visibility": false
                            },
                            {
                                "_key": "videoSource",
                                "_value": [],
                                "_type": "a",
                                "_attrDef": "p",
                                "_visibility": false
                            },
                            {
                                "_key": "audioDatasource",
                                "_value": "",
                                "_type": "a",
                                "_attrDef": "p",
                                "_visibility": false
                            },
                            {
                                "_key": "audioSrc",
                                "_value": "",
                                "_type": "a",
                                "_attrDef": "p",
                                "_visibility": false
                            },
                            {
                                "_key": "audioType",
                                "_value": "",
                                "_type": "a",
                                "_attrDef": "p",
                                "_visibility": false
                            },
                            {
                                "_key": "videoDatasource",
                                "_value": "",
                                "_type": "a",
                                "_attrDef": "p",
                                "_visibility": false
                            },
                            {
                                "_key": "videoSrc",
                                "_value": "",
                                "_type": "a",
                                "_attrDef": "p",
                                "_visibility": false
                            },
                            {
                                "_key": "videoType",
                                "_value": "",
                                "_type": "a",
                                "_attrDef": "p",
                                "_visibility": false
                            },
                            {
                                "_key": "(audioplay)",
                                "_value": "",
                                "_type": "a",
                                "_attrDef": "p",
                                "_visibility": false
                            },
                            {
                                "_key": "(videoplay)",
                                "_value": "",
                                "_type": "a",
                                "_attrDef": "p",
                                "_visibility": false
                            },
                            {
                                "_key": "(audiopause)",
                                "_value": "",
                                "_type": "kv",
                                "_attrDef": "p",
                                "_visibility": false
                            },
                            {
                                "_key": "(videopause)",
                                "_value": "",
                                "_type": "kv",
                                "_attrDef": "p",
                                "_visibility": false
                            },
                            {
                                "_key": "(audioended)",
                                "_value": "",
                                "_type": "kv",
                                "_attrDef": "p",
                                "_visibility": false
                            },
                            {
                                "_key": "(videoended)",
                                "_value": "",
                                "_type": "kv",
                                "_attrDef": "p",
                                "_visibility": false
                            }
                        ],
                        "0dbfd2bd-4961-f61d-c961-cb2ffe4fb960": {
                            "paletteKey": "html-editor",
                            "parentEditorKey": "9ce2b954-e2db-d48f-a0d7-a95f15996520",
                            "isAdvancedChildComponent": true,
                            "designerReference": [
                                {
                                    "_key": "style",
                                    "_value": "",
                                    "_type": "kv",
                                    "_attrDef": "p"
                                },
                                {
                                    "_key": "class",
                                    "_value": "",
                                    "_type": "dav",
                                    "_attrDef": "p"
                                },
                                {
                                    "_key": "html",
                                    "_value": "<h4>{{locales.thankyou}}</h4>\r\n",
                                    "_type": "a",
                                    "_attrDef": "p"
                                }
                            ]
                        }
                    }
                },
                "93b28a6d-5a47-1d1f-d625-9216b6106329": {
                    "paletteKey": "FlexLayoutRow",
                    "parentEditorKey": "c09b7c46-a8d6-f2da-bfff-9ea012cd5403",
                    "designerReference": [
                        {
                            "_key": "componentLabel",
                            "_value": "Row",
                            "_type": "kv",
                            "_attrDef": "p",
                            "_useAsLabel": true
                        },
                        {
                            "_key": "style",
                            "_value": "",
                            "_type": "kv",
                            "_attrDef": "p"
                        },
                        {
                            "_key": "class",
                            "_value": "",
                            "_type": "dav",
                            "_attrDef": "p"
                        },
                        {
                            "_key": "fxFlex",
                            "_value": "",
                            "_type": "kv",
                            "_attrDef": "p"
                        },
                        {
                            "_key": "fxLayoutGap",
                            "_value": "",
                            "_type": "kv",
                            "_attrDef": "p"
                        },
                        {
                            "_key": "wrap",
                            "_value": "wrap",
                            "_type": "a",
                            "_attrDef": "p"
                        },
                        {
                            "_key": "layoutAlign",
                            "_value": "start",
                            "_type": "a",
                            "_attrDef": "p"
                        },
                        {
                            "_key": "pLayoutAlign",
                            "_value": "stretch",
                            "_type": "a",
                            "_attrDef": "p"
                        },
                        {
                            "_key": "[fxShow]",
                            "_value": "true",
                            "_type": "kv",
                            "_attrDef": "p"
                        },
                        {
                            "_key": "[fxHide]",
                            "_value": "false",
                            "_type": "kv",
                            "_attrDef": "p"
                        }
                    ],
                    "bf3088e9-8cd8-d630-f783-00fc72a05d7f": {
                        "paletteKey": "FlexLayoutCol",
                        "parentEditorKey": "93b28a6d-5a47-1d1f-d625-9216b6106329",
                        "designerReference": [
                            {
                                "_key": "componentLabel",
                                "_value": "Column",
                                "_type": "kv",
                                "_attrDef": "p",
                                "_useAsLabel": true
                            },
                            {
                                "_key": "style",
                                "_value": "",
                                "_type": "kv",
                                "_attrDef": "p"
                            },
                            {
                                "_key": "class",
                                "_value": "",
                                "_type": "dav",
                                "_attrDef": "p"
                            },
                            {
                                "_key": "fxFlex",
                                "_value": "",
                                "_type": "kv",
                                "_attrDef": "p"
                            },
                            {
                                "_key": "fxLayoutGap",
                                "_value": "",
                                "_type": "kv",
                                "_attrDef": "p"
                            },
                            {
                                "_key": "wrap",
                                "_value": "wrap",
                                "_type": "a",
                                "_attrDef": "p"
                            },
                            {
                                "_key": "layoutAlign",
                                "_value": "space-evenly",
                                "_type": "a",
                                "_attrDef": "p"
                            },
                            {
                                "_key": "pLayoutAlign",
                                "_value": "center",
                                "_type": "a",
                                "_attrDef": "p"
                            },
                            {
                                "_key": "[fxShow]",
                                "_value": "true",
                                "_type": "kv",
                                "_attrDef": "p"
                            },
                            {
                                "_key": "[fxHide]",
                                "_value": "false",
                                "_type": "kv",
                                "_attrDef": "p"
                            }
                        ],
                        "3e8d995c-a429-0a1c-c2bb-bcd8a7abd212": {
                            "paletteKey": "Html5",
                            "parentEditorKey": "bf3088e9-8cd8-d630-f783-00fc72a05d7f",
                            "isAdvancedComponent": true,
                            "designerReference": [
                                {
                                    "_key": "style",
                                    "_value": "    ",
                                    "_type": "kv",
                                    "_attrDef": "p"
                                },
                                {
                                    "_key": "class",
                                    "_value": [
                                        "refferal_message_class"
                                    ],
                                    "_type": "dav",
                                    "_attrDef": "p"
                                },
                                {
                                    "_key": "htmlElement",
                                    "_value": "div",
                                    "_type": "dav",
                                    "_attrDef": "p",
                                    "_useAsLabel": true
                                },
                                {
                                    "_key": "tagType",
                                    "_value": "div",
                                    "_type": "a",
                                    "_attrDef": "p",
                                    "_visibility": false
                                },
                                {
                                    "_key": "name",
                                    "_value": "",
                                    "_type": "kv",
                                    "_attrDef": "p",
                                    "_visibility": false
                                },
                                {
                                    "_key": "sandbox",
                                    "_value": "",
                                    "_type": "kv",
                                    "_attrDef": "p",
                                    "_visibility": false
                                },
                                {
                                    "_key": "src",
                                    "_value": "",
                                    "_type": "kv",
                                    "_attrDef": "p",
                                    "_visibility": false
                                },
                                {
                                    "_key": "srcdoc",
                                    "_value": "",
                                    "_type": "kv",
                                    "_attrDef": "p",
                                    "_visibility": false
                                },
                                {
                                    "_key": "width",
                                    "_value": "",
                                    "_type": "kv",
                                    "_attrDef": "p",
                                    "_visibility": false
                                },
                                {
                                    "_key": "[autoplay]",
                                    "_value": "",
                                    "_type": "kv",
                                    "_attrDef": "p",
                                    "_visibility": false
                                },
                                {
                                    "_key": "[loop]",
                                    "_value": "",
                                    "_type": "kv",
                                    "_attrDef": "p",
                                    "_visibility": false
                                },
                                {
                                    "_key": "data",
                                    "_value": "",
                                    "_type": "kv",
                                    "_attrDef": "p",
                                    "_visibility": false
                                },
                                {
                                    "_key": "audioSource",
                                    "_value": [],
                                    "_type": "a",
                                    "_attrDef": "p",
                                    "_visibility": false
                                },
                                {
                                    "_key": "videoSource",
                                    "_value": [],
                                    "_type": "a",
                                    "_attrDef": "p",
                                    "_visibility": false
                                },
                                {
                                    "_key": "audioDatasource",
                                    "_value": "",
                                    "_type": "a",
                                    "_attrDef": "p",
                                    "_visibility": false
                                },
                                {
                                    "_key": "audioSrc",
                                    "_value": "",
                                    "_type": "a",
                                    "_attrDef": "p",
                                    "_visibility": false
                                },
                                {
                                    "_key": "audioType",
                                    "_value": "",
                                    "_type": "a",
                                    "_attrDef": "p",
                                    "_visibility": false
                                },
                                {
                                    "_key": "videoDatasource",
                                    "_value": "",
                                    "_type": "a",
                                    "_attrDef": "p",
                                    "_visibility": false
                                },
                                {
                                    "_key": "videoSrc",
                                    "_value": "",
                                    "_type": "a",
                                    "_attrDef": "p",
                                    "_visibility": false
                                },
                                {
                                    "_key": "videoType",
                                    "_value": "",
                                    "_type": "a",
                                    "_attrDef": "p",
                                    "_visibility": false
                                },
                                {
                                    "_key": "(audioplay)",
                                    "_value": "",
                                    "_type": "a",
                                    "_attrDef": "p",
                                    "_visibility": false
                                },
                                {
                                    "_key": "(videoplay)",
                                    "_value": "",
                                    "_type": "a",
                                    "_attrDef": "p",
                                    "_visibility": false
                                },
                                {
                                    "_key": "(audiopause)",
                                    "_value": "",
                                    "_type": "kv",
                                    "_attrDef": "p",
                                    "_visibility": false
                                },
                                {
                                    "_key": "(videopause)",
                                    "_value": "",
                                    "_type": "kv",
                                    "_attrDef": "p",
                                    "_visibility": false
                                },
                                {
                                    "_key": "(audioended)",
                                    "_value": "",
                                    "_type": "kv",
                                    "_attrDef": "p",
                                    "_visibility": false
                                },
                                {
                                    "_key": "(videoended)",
                                    "_value": "",
                                    "_type": "kv",
                                    "_attrDef": "p",
                                    "_visibility": false
                                }
                            ],
                            "45ceeca5-fceb-c48b-1dc6-2d0c352e7fc2": {
                                "paletteKey": "html-editor",
                                "parentEditorKey": "3e8d995c-a429-0a1c-c2bb-bcd8a7abd212",
                                "isAdvancedChildComponent": true,
                                "designerReference": [
                                    {
                                        "_key": "style",
                                        "_value": "",
                                        "_type": "kv",
                                        "_attrDef": "p"
                                    },
                                    {
                                        "_key": "class",
                                        "_value": "",
                                        "_type": "dav",
                                        "_attrDef": "p"
                                    },
                                    {
                                        "_key": "html",
                                        "_value": "{{locales.refferalMessage}}",
                                        "_type": "a",
                                        "_attrDef": "p"
                                    }
                                ]
                            }
                        }
                    }
                }
            },
            "6cdec833-2d37-1505-2da5-49b13b97cc53": {
                "paletteKey": "FlexLayoutRow",
                "parentEditorKey": "9fd1622a-7461-4520-a543-1b19da053f62",
                "designerReference": [
                    {
                        "_key": "componentLabel",
                        "_value": "Row",
                        "_type": "kv",
                        "_attrDef": "p",
                        "_useAsLabel": true
                    },
                    {
                        "_key": "style",
                        "_value": "width: 100%; padding-bottom: 1em",
                        "_type": "kv",
                        "_attrDef": "p"
                    },
                    {
                        "_key": "class",
                        "_value": "",
                        "_type": "dav",
                        "_attrDef": "p"
                    },
                    {
                        "_key": "fxFlex",
                        "_value": "",
                        "_type": "kv",
                        "_attrDef": "p"
                    },
                    {
                        "_key": "fxLayoutGap",
                        "_value": "",
                        "_type": "kv",
                        "_attrDef": "p"
                    },
                    {
                        "_key": "wrap",
                        "_value": "wrap",
                        "_type": "a",
                        "_attrDef": "p"
                    },
                    {
                        "_key": "layoutAlign",
                        "_value": "start",
                        "_type": "a",
                        "_attrDef": "p"
                    },
                    {
                        "_key": "pLayoutAlign",
                        "_value": "stretch",
                        "_type": "a",
                        "_attrDef": "p"
                    },
                    {
                        "_key": "[fxShow]",
                        "_value": "true",
                        "_type": "kv",
                        "_attrDef": "p"
                    },
                    {
                        "_key": "[fxHide]",
                        "_value": "false",
                        "_type": "kv",
                        "_attrDef": "p"
                    }
                ],
                "34d6c127-ba31-c8d5-fb9c-9636b5a5a514": {
                    "paletteKey": "FlexLayoutCol",
                    "parentEditorKey": "6cdec833-2d37-1505-2da5-49b13b97cc53",
                    "designerReference": [
                        {
                            "_key": "componentLabel",
                            "_value": "Column",
                            "_type": "kv",
                            "_attrDef": "p",
                            "_useAsLabel": true
                        },
                        {
                            "_key": "style",
                            "_value": "",
                            "_type": "kv",
                            "_attrDef": "p"
                        },
                        {
                            "_key": "class",
                            "_value": "",
                            "_type": "dav",
                            "_attrDef": "p"
                        },
                        {
                            "_key": "fxFlex",
                            "_value": "100",
                            "_type": "kv",
                            "_attrDef": "p"
                        },
                        {
                            "_key": "fxLayoutGap",
                            "_value": "",
                            "_type": "kv",
                            "_attrDef": "p"
                        },
                        {
                            "_key": "wrap",
                            "_value": "wrap",
                            "_type": "a",
                            "_attrDef": "p"
                        },
                        {
                            "_key": "layoutAlign",
                            "_value": "start",
                            "_type": "a",
                            "_attrDef": "p"
                        },
                        {
                            "_key": "pLayoutAlign",
                            "_value": "center",
                            "_type": "a",
                            "_attrDef": "p"
                        },
                        {
                            "_key": "[fxShow]",
                            "_value": "true",
                            "_type": "kv",
                            "_attrDef": "p"
                        },
                        {
                            "_key": "[fxHide]",
                            "_value": "false",
                            "_type": "kv",
                            "_attrDef": "p"
                        }
                    ],
                    "52cbda82-bcf2-e620-b399-9636928673f1": {
                        "paletteKey": "FlexLayoutRow",
                        "parentEditorKey": "34d6c127-ba31-c8d5-fb9c-9636b5a5a514",
                        "designerReference": [
                            {
                                "_key": "componentLabel",
                                "_value": "submittedby",
                                "_type": "kv",
                                "_attrDef": "p",
                                "_useAsLabel": true
                            },
                            {
                                "_key": "style",
                                "_value": "width:100%;",
                                "_type": "kv",
                                "_attrDef": "p"
                            },
                            {
                                "_key": "class",
                                "_value": "",
                                "_type": "dav",
                                "_attrDef": "p"
                            },
                            {
                                "_key": "fxFlex",
                                "_value": "",
                                "_type": "kv",
                                "_attrDef": "p"
                            },
                            {
                                "_key": "fxLayoutGap",
                                "_value": "",
                                "_type": "kv",
                                "_attrDef": "p"
                            },
                            {
                                "_key": "wrap",
                                "_value": "wrap",
                                "_type": "a",
                                "_attrDef": "p"
                            },
                            {
                                "_key": "layoutAlign",
                                "_value": "start",
                                "_type": "a",
                                "_attrDef": "p"
                            },
                            {
                                "_key": "pLayoutAlign",
                                "_value": "stretch",
                                "_type": "a",
                                "_attrDef": "p"
                            },
                            {
                                "_key": "[fxShow]",
                                "_value": "true",
                                "_type": "kv",
                                "_attrDef": "p"
                            },
                            {
                                "_key": "[fxHide]",
                                "_value": "false",
                                "_type": "kv",
                                "_attrDef": "p"
                            }
                        ],
                        "d7b47d13-3c89-866f-8d5c-43f52d33c8e6": {
                            "paletteKey": "FlexLayoutCol",
                            "parentEditorKey": "52cbda82-bcf2-e620-b399-9636928673f1",
                            "designerReference": [
                                {
                                    "_key": "componentLabel",
                                    "_value": "Column",
                                    "_type": "kv",
                                    "_attrDef": "p",
                                    "_useAsLabel": true
                                },
                                {
                                    "_key": "style",
                                    "_value": "",
                                    "_type": "kv",
                                    "_attrDef": "p"
                                },
                                {
                                    "_key": "class",
                                    "_value": "",
                                    "_type": "dav",
                                    "_attrDef": "p"
                                },
                                {
                                    "_key": "fxFlex",
                                    "_value": "100",
                                    "_type": "kv",
                                    "_attrDef": "p"
                                },
                                {
                                    "_key": "fxLayoutGap",
                                    "_value": "",
                                    "_type": "kv",
                                    "_attrDef": "p"
                                },
                                {
                                    "_key": "wrap",
                                    "_value": "wrap",
                                    "_type": "a",
                                    "_attrDef": "p"
                                },
                                {
                                    "_key": "layoutAlign",
                                    "_value": "start",
                                    "_type": "a",
                                    "_attrDef": "p"
                                },
                                {
                                    "_key": "pLayoutAlign",
                                    "_value": "stretch",
                                    "_type": "a",
                                    "_attrDef": "p"
                                },
                                {
                                    "_key": "[fxShow]",
                                    "_value": "true",
                                    "_type": "kv",
                                    "_attrDef": "p"
                                },
                                {
                                    "_key": "[fxHide]",
                                    "_value": "false",
                                    "_type": "kv",
                                    "_attrDef": "p"
                                }
                            ],
                            "e71ad384-6876-69e3-c1d2-fa7ad95d7bdd": {
                                "paletteKey": "Html5",
                                "parentEditorKey": "d7b47d13-3c89-866f-8d5c-43f52d33c8e6",
                                "isAdvancedComponent": true,
                                "designerReference": [
                                    {
                                        "_key": "style",
                                        "_value": "",
                                        "_type": "kv",
                                        "_attrDef": "p"
                                    },
                                    {
                                        "_key": "class",
                                        "_value": [
                                            "submitted_by"
                                        ],
                                        "_type": "dav",
                                        "_attrDef": "p"
                                    },
                                    {
                                        "_key": "htmlElement",
                                        "_value": "div",
                                        "_type": "dav",
                                        "_attrDef": "p",
                                        "_useAsLabel": true
                                    },
                                    {
                                        "_key": "tagType",
                                        "_value": "div",
                                        "_type": "a",
                                        "_attrDef": "p",
                                        "_visibility": false
                                    },
                                    {
                                        "_key": "name",
                                        "_value": "",
                                        "_type": "kv",
                                        "_attrDef": "p",
                                        "_visibility": false
                                    },
                                    {
                                        "_key": "sandbox",
                                        "_value": "",
                                        "_type": "kv",
                                        "_attrDef": "p",
                                        "_visibility": false
                                    },
                                    {
                                        "_key": "src",
                                        "_value": "",
                                        "_type": "kv",
                                        "_attrDef": "p",
                                        "_visibility": false
                                    },
                                    {
                                        "_key": "srcdoc",
                                        "_value": "",
                                        "_type": "kv",
                                        "_attrDef": "p",
                                        "_visibility": false
                                    },
                                    {
                                        "_key": "width",
                                        "_value": "",
                                        "_type": "kv",
                                        "_attrDef": "p",
                                        "_visibility": false
                                    },
                                    {
                                        "_key": "[autoplay]",
                                        "_value": "",
                                        "_type": "kv",
                                        "_attrDef": "p",
                                        "_visibility": false
                                    },
                                    {
                                        "_key": "[loop]",
                                        "_value": "",
                                        "_type": "kv",
                                        "_attrDef": "p",
                                        "_visibility": false
                                    },
                                    {
                                        "_key": "data",
                                        "_value": "",
                                        "_type": "kv",
                                        "_attrDef": "p",
                                        "_visibility": false
                                    },
                                    {
                                        "_key": "audioSource",
                                        "_value": [],
                                        "_type": "a",
                                        "_attrDef": "p",
                                        "_visibility": false
                                    },
                                    {
                                        "_key": "videoSource",
                                        "_value": [],
                                        "_type": "a",
                                        "_attrDef": "p",
                                        "_visibility": false
                                    },
                                    {
                                        "_key": "audioDatasource",
                                        "_value": "",
                                        "_type": "a",
                                        "_attrDef": "p",
                                        "_visibility": false
                                    },
                                    {
                                        "_key": "audioSrc",
                                        "_value": "",
                                        "_type": "a",
                                        "_attrDef": "p",
                                        "_visibility": false
                                    },
                                    {
                                        "_key": "audioType",
                                        "_value": "",
                                        "_type": "a",
                                        "_attrDef": "p",
                                        "_visibility": false
                                    },
                                    {
                                        "_key": "videoDatasource",
                                        "_value": "",
                                        "_type": "a",
                                        "_attrDef": "p",
                                        "_visibility": false
                                    },
                                    {
                                        "_key": "videoSrc",
                                        "_value": "",
                                        "_type": "a",
                                        "_attrDef": "p",
                                        "_visibility": false
                                    },
                                    {
                                        "_key": "videoType",
                                        "_value": "",
                                        "_type": "a",
                                        "_attrDef": "p",
                                        "_visibility": false
                                    },
                                    {
                                        "_key": "(audioplay)",
                                        "_value": "",
                                        "_type": "a",
                                        "_attrDef": "p",
                                        "_visibility": false
                                    },
                                    {
                                        "_key": "(videoplay)",
                                        "_value": "",
                                        "_type": "a",
                                        "_attrDef": "p",
                                        "_visibility": false
                                    },
                                    {
                                        "_key": "(audiopause)",
                                        "_value": "",
                                        "_type": "kv",
                                        "_attrDef": "p",
                                        "_visibility": false
                                    },
                                    {
                                        "_key": "(videopause)",
                                        "_value": "",
                                        "_type": "kv",
                                        "_attrDef": "p",
                                        "_visibility": false
                                    },
                                    {
                                        "_key": "(audioended)",
                                        "_value": "",
                                        "_type": "kv",
                                        "_attrDef": "p",
                                        "_visibility": false
                                    },
                                    {
                                        "_key": "(videoended)",
                                        "_value": "",
                                        "_type": "kv",
                                        "_attrDef": "p",
                                        "_visibility": false
                                    }
                                ],
                                "51a9eecb-5aa8-43f4-5cd1-d8ad607435d0": {
                                    "paletteKey": "html-editor",
                                    "parentEditorKey": "e71ad384-6876-69e3-c1d2-fa7ad95d7bdd",
                                    "isAdvancedChildComponent": true,
                                    "designerReference": [
                                        {
                                            "_key": "style",
                                            "_value": "",
                                            "_type": "kv",
                                            "_attrDef": "p"
                                        },
                                        {
                                            "_key": "class",
                                            "_value": "",
                                            "_type": "dav",
                                            "_attrDef": "p"
                                        },
                                        {
                                            "_key": "html",
                                            "_value": "{{locales.submittedby}}\r\n\r\n<div style=\"color: #283552;\r\n    padding-bottom: 1em;\r\n    padding-\r\n    text-align: center;\r\n    letter-spacing: 0.5px;\r\n    text-transform: capitalize;\r\n    width: 100%;\r\n    font-family: Poppins;\r\n    font-style: normal;\r\n    font-weight: 600;\r\n    font-size: 15px;\r\n    line-height: 30px;\">{{name}}</div>\r\n\r\n<div style=\"font-size: 2em;font-weight: 600;\">{{today}}</div>\r\n",
                                            "_type": "a",
                                            "_attrDef": "p"
                                        }
                                    ]
                                }
                            }
                        }
                    }
                }
            },
            "5ddc4377-2aa6-971b-278a-922c8436ade8": {
                "paletteKey": "NG-MiniFabButton",
                "parentEditorKey": "9fd1622a-7461-4520-a543-1b19da053f62",
                "designerReference": [
                    {
                        "_key": "style",
                        "_value": "",
                        "_type": "kv",
                        "_attrDef": "p"
                    },
                    {
                        "_key": "class",
                        "_value": [
                            "refferal_add"
                        ],
                        "_type": "dav",
                        "_attrDef": "p"
                    },
                    {
                        "_key": "fabicon",
                        "_value": "add",
                        "_type": "a",
                        "_attrDef": "p",
                        "_useAsLabel": true
                    },
                    {
                        "_key": "color",
                        "_value": "",
                        "_type": "kv",
                        "_attrDef": "p"
                    },
                    {
                        "_key": "(click)",
                        "_value": "",
                        "_type": "kv",
                        "_attrDef": "p"
                    },
                    {
                        "_key": "[disabled]",
                        "_value": "",
                        "_type": "kv",
                        "_attrDef": "p"
                    },
                    {
                        "_key": "[disableRipple]",
                        "_value": "",
                        "_type": "kv",
                        "_attrDef": "p"
                    },
                    {
                        "_key": "type",
                        "_value": "",
                        "_type": "kv",
                        "_attrDef": "p"
                    },
                    {
                        "_key": "routerLink",
                        "_value": "",
                        "_type": "kv",
                        "_attrDef": "p"
                    }
                ]
            },
            "dbcc0ba3-3730-d14c-70af-90fe2407d98c": {
                "paletteKey": "Html5",
                "parentEditorKey": "9fd1622a-7461-4520-a543-1b19da053f62",
                "isAdvancedComponent": true,
                "designerReference": [
                    {
                        "_key": "style",
                        "_value": "",
                        "_type": "kv",
                        "_attrDef": "p"
                    },
                    {
                        "_key": "class",
                        "_value": "",
                        "_type": "dav",
                        "_attrDef": "p"
                    },
                    {
                        "_key": "htmlElement",
                        "_value": "p",
                        "_type": "dav",
                        "_attrDef": "p",
                        "_useAsLabel": true
                    },
                    {
                        "_key": "tagType",
                        "_value": "p",
                        "_type": "a",
                        "_attrDef": "p",
                        "_visibility": false
                    },
                    {
                        "_key": "name",
                        "_value": "",
                        "_type": "kv",
                        "_attrDef": "p",
                        "_visibility": false
                    },
                    {
                        "_key": "sandbox",
                        "_value": "",
                        "_type": "kv",
                        "_attrDef": "p",
                        "_visibility": false
                    },
                    {
                        "_key": "src",
                        "_value": "",
                        "_type": "kv",
                        "_attrDef": "p",
                        "_visibility": false
                    },
                    {
                        "_key": "srcdoc",
                        "_value": "",
                        "_type": "kv",
                        "_attrDef": "p",
                        "_visibility": false
                    },
                    {
                        "_key": "width",
                        "_value": "",
                        "_type": "kv",
                        "_attrDef": "p",
                        "_visibility": false
                    },
                    {
                        "_key": "[autoplay]",
                        "_value": "",
                        "_type": "kv",
                        "_attrDef": "p",
                        "_visibility": false
                    },
                    {
                        "_key": "[loop]",
                        "_value": "",
                        "_type": "kv",
                        "_attrDef": "p",
                        "_visibility": false
                    },
                    {
                        "_key": "data",
                        "_value": "",
                        "_type": "kv",
                        "_attrDef": "p",
                        "_visibility": false
                    },
                    {
                        "_key": "audioSource",
                        "_value": [],
                        "_type": "a",
                        "_attrDef": "p",
                        "_visibility": false
                    },
                    {
                        "_key": "videoSource",
                        "_value": [],
                        "_type": "a",
                        "_attrDef": "p",
                        "_visibility": false
                    },
                    {
                        "_key": "audioDatasource",
                        "_value": "",
                        "_type": "a",
                        "_attrDef": "p",
                        "_visibility": false
                    },
                    {
                        "_key": "audioSrc",
                        "_value": "",
                        "_type": "a",
                        "_attrDef": "p",
                        "_visibility": false
                    },
                    {
                        "_key": "audioType",
                        "_value": "",
                        "_type": "a",
                        "_attrDef": "p",
                        "_visibility": false
                    },
                    {
                        "_key": "videoDatasource",
                        "_value": "",
                        "_type": "a",
                        "_attrDef": "p",
                        "_visibility": false
                    },
                    {
                        "_key": "videoSrc",
                        "_value": "",
                        "_type": "a",
                        "_attrDef": "p",
                        "_visibility": false
                    },
                    {
                        "_key": "videoType",
                        "_value": "",
                        "_type": "a",
                        "_attrDef": "p",
                        "_visibility": false
                    },
                    {
                        "_key": "(audioplay)",
                        "_value": "",
                        "_type": "a",
                        "_attrDef": "p",
                        "_visibility": false
                    },
                    {
                        "_key": "(videoplay)",
                        "_value": "",
                        "_type": "a",
                        "_attrDef": "p",
                        "_visibility": false
                    },
                    {
                        "_key": "(audiopause)",
                        "_value": "",
                        "_type": "kv",
                        "_attrDef": "p",
                        "_visibility": false
                    },
                    {
                        "_key": "(videopause)",
                        "_value": "",
                        "_type": "kv",
                        "_attrDef": "p",
                        "_visibility": false
                    },
                    {
                        "_key": "(audioended)",
                        "_value": "",
                        "_type": "kv",
                        "_attrDef": "p",
                        "_visibility": false
                    },
                    {
                        "_key": "(videoended)",
                        "_value": "",
                        "_type": "kv",
                        "_attrDef": "p",
                        "_visibility": false
                    }
                ],
                "baeccb3f-5a62-b0c9-3418-3ff6422abee0": {
                    "paletteKey": "html-editor",
                    "parentEditorKey": "dbcc0ba3-3730-d14c-70af-90fe2407d98c",
                    "isAdvancedChildComponent": true,
                    "designerReference": [
                        {
                            "_key": "style",
                            "_value": "",
                            "_type": "kv",
                            "_attrDef": "p"
                        },
                        {
                            "_key": "class",
                            "_value": "",
                            "_type": "dav",
                            "_attrDef": "p"
                        },
                        {
                            "_key": "html",
                            "_value": "Wish Create New Referral?",
                            "_type": "a",
                            "_attrDef": "p"
                        }
                    ]
                }
            },
            "82f0da26-9299-dffe-11d7-1a094844cc22": {
                "paletteKey": "FlexLayoutRow",
                "parentEditorKey": "9fd1622a-7461-4520-a543-1b19da053f62",
                "designerReference": [
                    {
                        "_key": "componentLabel",
                        "_value": "Row",
                        "_type": "kv",
                        "_attrDef": "p",
                        "_useAsLabel": true
                    },
                    {
                        "_key": "style",
                        "_value": "",
                        "_type": "kv",
                        "_attrDef": "p"
                    },
                    {
                        "_key": "class",
                        "_value": "",
                        "_type": "dav",
                        "_attrDef": "p"
                    },
                    {
                        "_key": "fxFlex",
                        "_value": "",
                        "_type": "kv",
                        "_attrDef": "p"
                    },
                    {
                        "_key": "fxLayoutGap",
                        "_value": "",
                        "_type": "kv",
                        "_attrDef": "p"
                    },
                    {
                        "_key": "wrap",
                        "_value": "wrap",
                        "_type": "a",
                        "_attrDef": "p"
                    },
                    {
                        "_key": "layoutAlign",
                        "_value": "center",
                        "_type": "a",
                        "_attrDef": "p"
                    },
                    {
                        "_key": "pLayoutAlign",
                        "_value": "center",
                        "_type": "a",
                        "_attrDef": "p"
                    },
                    {
                        "_key": "[fxShow]",
                        "_value": "true",
                        "_type": "kv",
                        "_attrDef": "p"
                    },
                    {
                        "_key": "[fxHide]",
                        "_value": "false",
                        "_type": "kv",
                        "_attrDef": "p"
                    }
                ],
                "dff6b83b-9bec-3e8a-6a48-8b4e6c8e25aa": {
                    "paletteKey": "NG-image",
                    "parentEditorKey": "82f0da26-9299-dffe-11d7-1a094844cc22",
                    "designerReference": [
                        {
                            "_key": "componentLabel",
                            "_value": "Image",
                            "_type": "kv",
                            "_attrDef": "p",
                            "_useAsLabel": true
                        },
                        {
                            "_key": "style",
                            "_value": "padding-bottom:2em ;",
                            "_type": "kv",
                            "_attrDef": "p"
                        },
                        {
                            "_key": "class",
                            "_value": "",
                            "_type": "dav",
                            "_attrDef": "p"
                        },
                        {
                            "_key": "imgSrc",
                            "_value": "Android/message.png",
                            "_type": "kv",
                            "_attrDef": "p"
                        },
                        {
                            "_key": "alt",
                            "_value": "",
                            "_type": "kv",
                            "_attrDef": "p"
                        },
                        {
                            "_key": "[src]",
                            "_value": "",
                            "_type": "kv",
                            "_attrDef": "p"
                        },
                        {
                            "_key": "imgSecure",
                            "_value": "",
                            "_type": "a",
                            "_attrDef": "p"
                        },
                        {
                            "_key": "[collectionName]",
                            "_value": "",
                            "_type": "kv",
                            "_attrDef": "p"
                        },
                        {
                            "_key": "[imageFilter]",
                            "_value": "",
                            "_type": "kv",
                            "_attrDef": "p"
                        },
                        {
                            "_key": "width",
                            "_value": "",
                            "_type": "kv",
                            "_attrDef": "p"
                        },
                        {
                            "_key": "srcset",
                            "_value": "",
                            "_type": "kv",
                            "_attrDef": "p"
                        },
                        {
                            "_key": "sizes",
                            "_value": "",
                            "_type": "kv",
                            "_attrDef": "p"
                        }
                    ]
                }
            }
        }
    }
}
